freeform.html
freeform.rst
setup.cfg
setup.py
data/example-1.forms
data/session.ffb
data/test_disambiguate_on_singular_param_position.ffb
data/test_menu_vs_listmenu.ffs
ez_setup/README.txt
ez_setup/__init__.py
freeform/__init__.py
freeform/formtable.py
freeform/levenshtein.py
freeform/match.py
freeform/tool.py
freeform.egg-info/PKG-INFO
freeform.egg-info/SOURCES.txt
freeform.egg-info/entry_points.txt
freeform.egg-info/top_level.txt
freeform_tests/__init__.py
freeform_tests/profile_match.py
freeform_tests/test_all.py
freeform_tests/test_formtable.py
freeform_tests/test_match.py
