Metadata-Version: 1.0
Name: freeform
Version: 0.3
Summary: natural interpretation of loosely structured user phrases
Home-page: http://svn.wiretooth.com/downloads/freeform.html
Author: Robin Bryce
Author-email: robin@wiretooth.com
License: Choose either AFL v3.0 or MIT
Download-URL: http://svn.wiretooth.com/downloads/freeform.html
Platform: UNKNOWN
Classifier: Development Status :: 1 - alpha
Classifier: Environment :: Console
Classifier: Environment :: Web Environment
Classifier: Intended Audience :: Developers
Classifier: License :: OSI Approved :: Academic Free v3.0 OR MIT
Classifier: Programming Language :: Python
